LICENSE
LICENSE.3rdparty
MANIFEST.in
README
pyproject.toml
setup.py
akida_models/__init__.py
akida_models/cli.py
akida_models/cyclic_lr.py
akida_models/distiller.py
akida_models/extract.py
akida_models/gamma_constraint.py
akida_models/layer_blocks.py
akida_models/model_io.py
akida_models/optimizers.py
akida_models/param_scheduler.py
akida_models/sparsity.py
akida_models/training.py
akida_models/unfuse_sepconv_layers.py
akida_models/utils.py
akida_models/version.py
akida_models.egg-info/PKG-INFO
akida_models.egg-info/SOURCES.txt
akida_models.egg-info/dependency_links.txt
akida_models.egg-info/entry_points.txt
akida_models.egg-info/requires.txt
akida_models.egg-info/top_level.txt
akida_models/casia_webface/__init__.py
akida_models/casia_webface/preprocessing.py
akida_models/centernet/__init__.py
akida_models/centernet/centernet_loss.py
akida_models/centernet/centernet_processing.py
akida_models/centernet/centernet_train.py
akida_models/centernet/centernet_utils.py
akida_models/centernet/model_centernet.py
akida_models/detection/__init__.py
akida_models/detection/box_utils.py
akida_models/detection/data.py
akida_models/detection/data_augmentation.py
akida_models/detection/data_utils.py
akida_models/detection/generate_anchors.py
akida_models/detection/map_evaluation.py
akida_models/detection/model_yolo.py
akida_models/detection/preprocess_data.py
akida_models/detection/processing.py
akida_models/detection/yolo_loss.py
akida_models/detection/yolo_train.py
akida_models/detection/coco/__init__.py
akida_models/detection/coco/data.py
akida_models/detection/voc/__init__.py
akida_models/detection/voc/data.py
akida_models/detection/widerface/__init__.py
akida_models/detection/widerface/data.py
akida_models/dvs/__init__.py
akida_models/dvs/dvs_generator.py
akida_models/dvs/dvs_train.py
akida_models/dvs/model_convtiny.py
akida_models/dvs/preprocessing.py
akida_models/imagenet/__init__.py
akida_models/imagenet/imagenet_labels2names.py
akida_models/imagenet/imagenet_train.py
akida_models/imagenet/imagenet_utils.py
akida_models/imagenet/load_samples.py
akida_models/imagenet/model_akidanet.py
akida_models/imagenet/model_akidanet18.py
akida_models/imagenet/model_akidanet_edge.py
